Metadata-Version: 2.1
Name: scireader
Version: 0.0.4
Summary: ScispaCy-based natural language processing pipeline for scientific literature mining
Home-page: https://github.com/yubailibra/scireader
Author: Yu Bai,Yunchen Yang
Author-email: yubailibra@yahoo.com
License: MIT license
Keywords: scireader
Platform: UNKNOWN
Classifier: Intended Audience :: Science/Research
Classifier: License :: OSI Approved :: MIT License
Classifier: Natural Language :: English
Classifier: Programming Language :: Python :: 3.6
Classifier: Programming Language :: Python :: 3.7
Requires-Python: >=3.6
